codableopt/__init__.py
codableopt/package_info.py
codableopt/interface/__init__.py
codableopt/interface/interface.py
codableopt/interface/system_args_map.py
codableopt/interface/system_constraint.py
codableopt/interface/system_objective.py
codableopt/interface/system_problem.py
codableopt/interface/system_variable.py
codableopt/solver/__init__.py
codableopt/solver/opt_solver.py
codableopt/solver/formulation/__init__.py
codableopt/solver/formulation/solver_problem.py
codableopt/solver/formulation/args_map/__init__.py
codableopt/solver/formulation/args_map/solver_args_map.py
codableopt/solver/formulation/constraint/__init__.py
codableopt/solver/formulation/constraint/solver_constraints.py
codableopt/solver/formulation/constraint/solver_liner_constraints.py
codableopt/solver/formulation/constraint/solver_user_define_constraint.py
codableopt/solver/formulation/objective/__init__.py
codableopt/solver/formulation/objective/solver_objective.py
codableopt/solver/formulation/variable/__init__.py
codableopt/solver/formulation/variable/solver_category_variable.py
codableopt/solver/formulation/variable/solver_double_variable.py
codableopt/solver/formulation/variable/solver_integer_variable.py
codableopt/solver/formulation/variable/solver_variable.py
codableopt/solver/formulation/variable/solver_variable_factory.py
codableopt/solver/optimizer/__init__.py
codableopt/solver/optimizer/optimization_solver.py
codableopt/solver/optimizer/optimization_state.py
codableopt/solver/optimizer/optimizer.py
codableopt/solver/optimizer/entity/__init__.py
codableopt/solver/optimizer/entity/proposal_to_move.py
codableopt/solver/optimizer/entity/score_info.py
codableopt/solver/optimizer/method/__init__.py
codableopt/solver/optimizer/method/optimizer_method.py
codableopt/solver/optimizer/method/penalty_adjustment_method.py
codableopt/solver/sampler/__init__.py
codableopt/solver/sampler/var_value_array_sampler.py
sample/__init__.py
sample/usage/__init__.py
sample/usage/problem/__init__.py
codableopt-0.1.2.dist-info/LICENSE.txt
codableopt-0.1.2.dist-info/METADATA
codableopt-0.1.2.dist-info/WHEEL
codableopt-0.1.2.dist-info/top_level.txt
codableopt-0.1.2.dist-info/RECORD
