Metadata-Version: 2.1
Name: codableopt
Version: 0.1.2
Summary: Optimization problem meta-heuristics solver for easy modeling.
Home-page: https://github.com/recruit-tech/codable-model-optimizer
Download-URL: https://github.com/recruit-tech/codable-model-optimizer
Author: Tomomitsu Motohashi, Kotaro Tanahashi
Author-email: tomomoto1983@gmail.com, tanahashi@r.recruit.co.jp
Maintainer: Kotaro Tanahashi
Maintainer-email: tanahashi@r.recruit.co.jp
License: Apache 2.0
Keywords: optimization,solver,modeling,meta-heuristics,mathematical optimization
Requires-Python: >=3.7, <3.11
License-File: LICENSE.txt
Requires-Dist: numpy (>=1.22.0)
